lstm_tools/__init__.py
lstm_tools/base.py
lstm_tools/chronicle.py
lstm_tools/exceptions.py
lstm_tools/feature.py
lstm_tools/logger.py
lstm_tools/sample.py
lstm_tools/settings.py
lstm_tools/timeframe.py
lstm_tools/utils.py
lstm_tools-0.4.1.dist-info/licenses/LICENSE
tests/__init__.py
tests/test_feature.py
lstm_tools-0.4.1.dist-info/METADATA
lstm_tools-0.4.1.dist-info/WHEEL
lstm_tools-0.4.1.dist-info/top_level.txt
lstm_tools-0.4.1.dist-info/RECORD
