Metadata-Version: 2.4
Name: lstm-tools
Version: 0.4.1
Summary: A high-performance library for dynamically handling sequential data
Home-page: https://github.com/heleusbrands/lstm-tools
Author: Rose Bloom Research Co
Author-email: rosebloomresearch@gmail.com
License: GPL-3.0-only
Keywords: lstm,time series,sequential data,windowing,data compression,dataframe,numpy,torch,tensorflow,pytorch,scikit-learn,plotly,line_profiler
Classifier: Programming Language :: Python :: 3
Classifier: License :: OSI Approved :: GNU General Public License v3 (GPLv3)
Classifier: Operating System :: OS Independent
Requires-Python: >=3.9
License-File: LICENSE
Requires-Dist: numpy
Requires-Dist: pandas
Requires-Dist: scikit-learn
Requires-Dist: torch
Requires-Dist: tensorflow
Requires-Dist: plotly
Requires-Dist: line_profiler
Dynamic: author
Dynamic: author-email
Dynamic: classifier
Dynamic: description
Dynamic: description-content-type
Dynamic: home-page
Dynamic: keywords
Dynamic: license
Dynamic: license-file
Dynamic: requires-dist
Dynamic: requires-python
Dynamic: summary
